LICENSE.txt
MANIFEST.in
README.txt
setup.py
Glams.egg-info/PKG-INFO
Glams.egg-info/SOURCES.txt
Glams.egg-info/dependency_links.txt
Glams.egg-info/requires.txt
Glams.egg-info/top_level.txt
glams/__init__.py
glams/backup_restore.py
glams/main.py
glams/setup_glams.py
glams/glams/__init__.py
glams/glams/glamsTemplate.py
glams/glams/checkpassword/__init__.py
glams/glams/checkpassword/checkpassword.py
glams/glams/databaseInterface/__init__.py
glams/glams/databaseInterface/connect.py
glams/glams/databaseInterface/databaseInterface.py
glams/glams/databaseInterface/reset.py
glams/glams/databaseInterface/users.py
glams/glams/website/__init__.py
glams/glams/website/admin/__init__.py
glams/glams/website/admin/admin.py
glams/glams/website/cal/__init__.py
glams/glams/website/cal/cal.py
glams/glams/website/database/__init__.py
glams/glams/website/database/classes.py
glams/glams/website/database/database.py
glams/glams/website/database/forms.py
glams/glams/website/experimentlog/__init__.py
glams/glams/website/experimentlog/experimentlog.py
glams/glams/website/home/__init__.py
glams/glams/website/home/home.py
glams/glams/website/home/login.py
glams/glams/website/home/settings.py
glams/glams/website/home/ajax/__init__.py
glams/glams/website/home/ajax/ajax.py
glams/glams/website/info/__init__.py
glams/glams/website/info/info.py
glams/support/css/almanacstyle.css
glams/support/css/database.css
glams/support/css/dragtable-default.css
glams/support/css/dragtable.css
glams/support/css/homepage.css
glams/support/css/searchform.css
glams/support/css/sharebubble.css
glams/support/css/home/home.css
glams/support/images/drag-handle.png
glams/support/images/homepagebg.jpg
glams/support/images/neurons.png
glams/support/images/trash.png
glams/support/images/trash.svg
glams/support/images/x.gif
glams/support/images/x2.gif
glams/support/javascript/databaseInterface.js
glams/support/javascript/experimentlog.js
glams/support/javascript/glamsscript.js
glams/support/javascript/jquery-color.js
glams/support/javascript/jquery-ui.js
glams/support/javascript/jquery.dragtable.js
glams/support/javascript/jquery.js
