Metadata-Version: 1.0
Name: Glams
Version: 0.2.5
Summary: A browser based animal management system
Home-page: https://github.com/kyleellefsen/Glams/
Author: Kyle Ellefsen
Author-email: kyleellefsen@gmail.com
License: MIT
Platform: UNKNOWN
